amsr/__init__.py
amsr/aromatics.py
amsr/atom.py
amsr/bfs.py
amsr/bond.py
amsr/bridgehead.py
amsr/check.py
amsr/conf.py
amsr/count.py
amsr/decode.py
amsr/encode.py
amsr/groups.py
amsr/lstm.py
amsr/markov.py
amsr/modifier.py
amsr/morph.py
amsr/mreplace.py
amsr/parity.py
amsr/pibonds.py
amsr/tokens.py
amsr/valence.py
amsr/version.py
amsr-0.1.6.dist-info/licenses/LICENSE
amsr-0.1.6.dist-info/METADATA
amsr-0.1.6.dist-info/WHEEL
amsr-0.1.6.dist-info/top_level.txt
amsr-0.1.6.dist-info/RECORD
