Metadata-Version: 2.4
Name: amsr
Version: 0.1.6
Summary: Another molecular string representation
Author: Harry Stern
License: MIT License
Classifier: Programming Language :: Python :: 3
Classifier: License :: OSI Approved :: MIT License
Classifier: Operating System :: OS Independent
Classifier: Topic :: Scientific/Engineering :: Chemistry
Requires-Python: >=3.9
License-File: LICENSE
Requires-Dist: rdkit
Requires-Dist: networkx
Requires-Dist: anytree
Requires-Dist: Levenshtein
Requires-Dist: typer
Requires-Dist: pandas
Requires-Dist: torch<3,>=2.4
Provides-Extra: dev
Requires-Dist: pytest>=8; extra == "dev"
Requires-Dist: pytest-cov>=5; extra == "dev"
Requires-Dist: pre-commit>=4; extra == "dev"
Requires-Dist: ruff>=0.5; extra == "dev"
Requires-Dist: mypy>=1.10; extra == "dev"
Provides-Extra: docs
Requires-Dist: sphinx>=7.3; extra == "docs"
Requires-Dist: furo>=2024.8.6; extra == "docs"
Requires-Dist: myst-parser>=3.0; extra == "docs"
Requires-Dist: sphinx-autodoc-typehints>=2.1; extra == "docs"
Provides-Extra: gpu
Requires-Dist: torch<3,>=2.4; extra == "gpu"
Requires-Dist: torchvision<0.25,>=0.19; extra == "gpu"
Requires-Dist: torchaudio<3,>=2.4; extra == "gpu"
Dynamic: license-file
